[["0",{"pageContent":"This restaurant is located in Jln.Sudirman in Jakarta City\nThis restaurant provides delicious local foods in Jakarta\nThe signature menu of this restaurant are : Ketoprak with price Rp 20.000 and Soto Betawi Rp 18.000\nThis restaurant is cheap yet popular in such big city!","metadata":{"id":0}}],["1",{"pageContent":"This restaurant is located in Jln.Tunjungan in Surabaya City\nThis restaurant provides delicious local foods in Surabaya\nThe signature menu of this restaurant are : Rawon Setan with price Rp 15.000, Lontong Balap with price Rp 12.000 and Rendang with price Rp15.000\nThis restaurant is cheap yet popular in such Beautiful city!","metadata":{"id":1}}]]